Workbook

Sheet VENDAS_PCP
E1: ALUFORCE LTDA. RUA ERNESTINA 270 - VILA SÃO JOÃO - 08537400 - FERRAZ DE VASCONCELOS - SP
A4: Orçamento: | C4: ORC-TESTE-2025 | D4: Revisão: | F4: Pedido: | G4: PED-TESTE-2025 | H4: Dt. liberação: | J4: 46016.125
A6: VENDEDOR: | C6: Carlos Silva | F6: Prazo de entrega: | H6: 15 dias uteis | M6: ;
A7: Cliente: | C7: ACME Industria e Comercio Ltda
A8: Contato: | C8: Joao da Silva | G8: Fone: | H8: 11999998888
A9: Email: | C9: joao@acme.com.br | H9: Frete: | J9: CIF
A11: Dados da transportadora: | M11: Frete | N11: Embalagens | O11: Forma de Pagamento | P11: Método de Pagamento | Q11: %
A12: Nome: | C12: Trans Express | G12: Fone: | H12: 1133334444 | M12: FOB | N12: Bobina | O12: Á VISTA | P12: TRANSFERÊNCIA | Q12: 0.2
A13: Cep: | C13: 01310-100 | E13: Endereço: | F13: Av Paulista 1000 | M13: CIF | N13: Rolo | O13: PARCELADO | P13: DEPÓSITO | Q13: 0.3
A14: Dados para cobrança: | D14: nfe@transexpress.com.br | N14: Lance | O14: ANTECIPADO | P14: FATURAMENTO | Q14: 0.5
A15: CPF/CNPJ: | C15: 12345678000199 | F15: E-mail Nfe: | G15: nfe@transexpress.com.br | N15: caixa | O15: ENTREGA | Q15: 1
B17: Cod. | C17: Produto | F17: Embalagem: | G17: Lance(s) | H17: Qtd. | I17: V. Un. R$ | J17: V. Total. R$
A18: 1 | B18: DUN16 | C18: =IFERROR(VLOOKUP(B18:B32,N18:O198,2,0),"") | F18: Bobina | G18: 500m | H18: 100 | I18: 15.5 | J18: 1550 | M18: VENDEDOR | N18: PRODUTO | O18: DESCRIÇÃO
A19: 2 | B19: TRN50 | C19: =IFERROR(VLOOKUP(B18:B32,N19:O199,2,0),"") | F19: Bobina | G19: 300m | H19: 50 | I19: 32.75 | J19: 1637.5 | M19: Renata Alves | N19: DUN10 | O19: ALUFORCE CB DUPLEX 10mm² NEUTRO NÚ
A20: 3 | B20: ; | C20: =IFERROR(VLOOKUP(B18:B32,N19:O200,2,0),"") | J20: 0 | M20: Augusto Ladeira | N20: DUN16 | O20: ALUFORCE CB DUPLEX 16mm² NEUTRO NÚ
A21: 4 | C21: =IFERROR(VLOOKUP(B18:B32,N19:O201,2,0),"") | J21: 0 | M21: Fabíola Souza | N21: DUN25 | O21: ALUFORCE CB DUPLEX 25mm² NEUTRO NÚ
A22: 5 | C22: =IFERROR(VLOOKUP(B18:B32,N19:O202,2,0),"") | J22: 0 | M22: Tainá Freitas | N22: DUN35 | O22: ALUFORCE CB DUPLEX 35mm² NEUTRO NÚ
A23: 6 | C23: =IFERROR(VLOOKUP(B18:B32,N19:O199,2,0),"") | J23: 0 | M23: Ariel Silva | N23: DUN50 | O23: ALUFORCE CB DUPLEX 50mm² NEUTRO NÚ
A24: 7 | C24: =IFERROR(VLOOKUP(B24:B38,N24:O204,2,0),"") | J24: 0 | M24: Marcia Scarcella | N24: DUI10 | O24: ALUFORCE CB DUPLEX 10mm² NEUTRO ISOLADO
A25: 8 | C25: =IFERROR(VLOOKUP(B18:B32,N18:O198,2,0),"") | J25: 0 | M25: Andréia Trovão | N25: DUI16 | O25: ALUFORCE CB DUPLEX 16mm² NEUTRO ISOLADO
A26: 9 | C26: =IFERROR(VLOOKUP(B18:B32,N18:O198,2,0),"") | J26: 0 | M26: Marcos Oliveira | N26: DUI25 | O26: ALUFORCE CB DUPLEX 25mm² NEUTRO ISOLADO
A27: 10 | C27: =IFERROR(VLOOKUP(B18:B32,N19:O207,2,0),"") | J27: 0 | N27: DUI35 | O27: ALUFORCE CB DUPLEX 35mm² NEUTRO ISOLADO
A28: 11 | C28: =IFERROR(VLOOKUP(B18:B32,N19:O199,2,0),"") | J28: 0 | N28: DUI50 | O28: ALUFORCE CB DUPLEX 50mm² NEUTRO ISOLADO
A29: 12 | C29: =IFERROR(VLOOKUP(B18:B32,N18:O198,2,0),"") | J29: 0 | N29: TRN10 | O29: ALUFORCE CB TRIPLEX 10mm² NEUTRO NÚ
A30: 13 | C30: =IFERROR(VLOOKUP(B18:B32,N19:O199,2,0),"") | J30: 0 | N30: TRN16 | O30: ALUFORCE CB TRIPLEX 16mm² NEUTRO NÚ
A31: 14 | C31: =IFERROR(VLOOKUP(B18:B32,N19:O199,2,0),"") | J31: 0 | N31: TRN25 | O31: ALUFORCE CB TRIPLEX 25mm² NEUTRO NÚ
A32: 15 | C32: =IFERROR(VLOOKUP(B18:B32,N19:O199,2,0),"") | J32: 0 | N32: TRN35 | O32: ALUFORCE CB TRIPLEX 35mm² NEUTRO NÚ
N33: TRN50/35 | O33: ALUFORCE CB TRIPLEX 50mm² + 35mm² NEUTRO NÚ
I34: Total do Pedido:$ | N34: TRN50 | O34: ALUFORCE CB TRIPLEX 50mm² NEUTRO NÚ
I35: 3187.5 | N35: TRN70 | O35: ALUFORCE CB TRIPLEX 70mm² NEUTRO NÚ
A36: Observações do Pedido | N36: TRN95/70 | O36: ALUFORCE CB TRIPLEX 95mm² + 70mm² NEUTRO NÚ
N37: TRN95 | O37: ALUFORCE CB TRIPLEX 95mm² NEUTRO NÚ
N38: TRN120/70 | O38: ALUFORCE CB TRIPLEX 120mm² + 70mm² NEUTRO NÚ
N39: TRN120/95 | O39: ALUFORCE CB TRIPLEX 120mm² + 95mm² NEUTRO NÚ
N40: TRN120 | O40: ALUFORCE CB TRIPLEX 120mm² NEUTRO NÚ
N41: TRN150/95 | O41: ALUFORCE CB TRIPLEX 150mm² + 95mm² NEUTRO NÚ
N42: TRN150/120 | O42: ALUFORCE CB TRIPLEX 150mm² + 120mm² NEUTRO NÚ
A43: CONDIÇOES DE PAGAMENTO. | N43: TRN150 | O43: ALUFORCE CB TRIPLEX 150mm² NEUTRO NÚ
A44: FORMAS DE PAGAMENTO | E44: % | F44: Método de Pagamento | I44: Valor Total $ | N44: TRN185/120 | O44: ALUFORCE CB TRIPLEX 185mm² + 120mm² NEUTRO NÚ
A45: PARCELADO | E45: 1 | F45: FATURAMENTO | I45: 3187.5 | N45: TRN185/150 | O45: ALUFORCE CB TRIPLEX 185mm² + 150mm² NEUTRO NÚ
A46: ENTREGA | E46: =100%-E45 -> 0 | N46: TRN185 | O46: ALUFORCE CB TRIPLEX 185mm² NEUTRO NÚ
N47: TRI10 | O47: ALUFORCE CB TRIPLEX 10mm² NEUTRO ISOLADO
A48: QTD - VOLUME: | D48: __________________________ | F48: EMBALAGEM: | H48: ___________________________ | N48: TRI16 | O48: ALUFORCE CB TRIPLEX 16mm² NEUTRO ISOLADO
N49: TRI25 | O49: ALUFORCE CB TRIPLEX 25mm² NEUTRO ISOLADO
E50: OBSERVAÇÕES: | N50: TRI35 | O50: ALUFORCE CB TRIPLEX 35mm² NEUTRO ISOLADO
C51: COMPLETO | N51: TRI50 | O51: ALUFORCE CB TRIPLEX 50mm² NEUTRO ISOLADO
N52: TRI50/35 | O52: ALUFORCE CB TRIPLEX 50mm² + 35mm² NEUTRO ISOLADO
C53: PARCIAL | N53: TRI70 | O53: ALUFORCE CB TRIPLEX 70mm² NEUTRO ISOLADO
N54: TRI95/70 | O54: ALUFORCE CB TRIPLEX 95mm² + 70mm² NEUTRO ISOLADO
N55: TRI95 | O55: ALUFORCE CB TRIPLEX 95mm² NEUTRO ISOLADO
N56: TRI120/70 | O56: ALUFORCE CB TRIPLEX 120mm² + 70mm² NEUTRO ISOLADO
N57: TRI120/95 | O57: ALUFORCE CB TRIPLEX 120mm² + 95mm² NEUTRO ISOLADO
N58: TRI120 | O58: ALUFORCE CB TRIPLEX 120mm² NEUTRO ISOLADO
N59: TRI150/95 | O59: ALUFORCE CB TRIPLEX 150mm² + 95mm² NEUTRO ISOLADO
N60: TRI150/120 | O60: ALUFORCE CB TRIPLEX 150mm² + 120mm² NEUTRO ISOLADO
N61: TRI150 | O61: ALUFORCE CB TRIPLEX 150mm² NEUTRO ISOLADO
N62: TRI185/120 | O62: ALUFORCE CB TRIPLEX 185mm² + 120mm² NEUTRO ISOLADO
N63: TRI185/150 | O63: ALUFORCE CB TRIPLEX 185mm² + 150mm² NEUTRO ISOLADO
N64: TRI185 | O64: ALUFORCR CB TRIPLEX 185mm² NEUTRO ISOLADO
N65: QDN10 | O65: ALUFORCE CB QUAD 10mm² NEUTRO NÚ
... N174: QDN150/70 | O174: ALUFORCE CB QUAD 150mm² + 70 mm² NEUTRO NÚ

Sheet PRODUÇÃO
E1: ALUFORCE LTDA. RUA ERNESTINA 270 - VILA SÃO JOÃO - 08537400 - FERAZ DE VASCONCELOS - SP
A3: X
A4: Orçamento: | C4: =VENDAS_PCP!C4 -> 0 | D4: Revisão: | E4: =VENDAS_PCP!E4 -> 0 | F4: Pedido: | G4: =VENDAS_PCP!G4 -> 0 | H4: Dt. liberação: | J4: =VENDAS_PCP!J4 -> 0
A6: VENDEDOR: | C6: =VENDAS_PCP!C6 -> 0 | F6: Prazo de entrega: | H6: =VENDAS_PCP!H6 -> 30
A7: Cliente: | C7: =VENDAS_PCP!C7 -> 0
A8: Contato: | C8: =VENDAS_PCP!C8 -> Rodrigo | G8: Fone: | H8: =VENDAS_PCP!H8 -> 0
A9: Email: | C9: =VENDAS_PCP!C9 -> 0 | H9: Frete: | J9: =VENDAS_PCP!J9 -> FOB
M11: Frete | N11: Embalagens | O11: Forma de Pagamento | P11: Método de Pagamento | Q11: %
B12: Cod. | C12: Produto | F12: Cod. Cores | H12: Embalagem: | I12: Lance(s) | J12: Qtd. | M12: FOB | N12: Bobina | O12: Á VISTA | P12: TRANSFERÊNCIA | Q12: 0.2
A13: 1 | B13: =VENDAS_PCP!B18 -> 0 | C13: =IFERROR(VLOOKUP(B13:B56,N18:O175,2,0),"") | F13: =IFERROR(VLOOKUP(B13,N18:P184,3,0),"") | H13: =VENDAS_PCP!F18 -> 0 | I13: =VENDAS_PCP!G18 -> 0 | J13: =VENDAS_PCP!H18 -> 0 | M13: CIF | N13: Rolo | O13: PARCELADO | P13: DEPÓSITO | Q13: 0.3
A14: P. BRUTO | D14: P.LIQUIDO | F14: LOTE | H14: =H13 -> 0 | N14: Lance | O14: ANTECIPADO | P14: FATURADO | Q14: 0.5
N15: caixa | O15: ENTREGA
A16: 2 | B16: =VENDAS_PCP!B19 -> 0 | C16: =IFERROR(VLOOKUP(B13:B56,N19:O175,2,0),"") | F16: =IFERROR(VLOOKUP(B16,N19:P188,3,0),"") | H16: =VENDAS_PCP!F19 -> 0 | I16: =VENDAS_PCP!G19 -> 0 | J16: =VENDAS_PCP!H19 -> 0
A17: P. BRUTO | D17: P.LIQUIDO | F17: LOTE | H17: =H16 -> 0
N18: PRODUTO | O18: DESCRIÇÃO | P18: Cod. Cores
A19: 3 | B19: =VENDAS_PCP!B20 -> ; | C19: =IFERROR(VLOOKUP(B13:B56,N18:O176,2,0),"") | F19: =IFERROR(VLOOKUP(B19,N18:P188,3,0),"") | H19: =VENDAS_PCP!F20 -> 0 | I19: =VENDAS_PCP!G20 -> 0 | J19: =VENDAS_PCP!H20 -> 0 | N19: DUN10 | O19: ALUFORCE CB DUPLEX 10mm² NEUTRO NÚ | P19: PT/NU
A20: P. BRUTO | D20: P.LIQUIDO | F20: LOTE | H20: =H19 -> 0 | N20: DUN16 | O20: ALUFORCE CB DUPLEX 16mm² NEUTRO NÚ | P20: PT/NU
N21: DUN25 | O21: ALUFORCE CB DUPLEX 25mm² NEUTRO NÚ | P21: PT/NU
A22: 4 | B22: =VENDAS_PCP!B21 -> 0 | C22: =IFERROR(VLOOKUP(B13:B56,N19:O175,2,0),"") | F22: =IFERROR(VLOOKUP(B22,N18:P186,3,0),"") | H22: =VENDAS_PCP!F21 -> 0 | I22: =VENDAS_PCP!G21 -> 0 | J22: =VENDAS_PCP!H21 -> 0 | N22: DUN35 | O22: ALUFORCE CB DUPLEX 35mm² NEUTRO NÚ | P22: PT/NU
A23: P. BRUTO | D23: P.LIQUIDO | F23: LOTE | H23: =H22 -> 0 | N23: DUN50 | O23: ALUFORCE CB DUPLEX 50mm² NEUTRO NÚ | P23: PT/NU
N24: DUI10 | O24: ALUFORCE CB DUPLEX 10mm² NEUTRO ISOLADO | P24: PT/AZ
A25: 5 | B25: =VENDAS_PCP!B22 -> 0 | C25: =C1 -> 0 | F25: =IFERROR(VLOOKUP(B25,N18:P188,3,0),"") | H25: =VENDAS_PCP!F22 -> 0 | I25: =VENDAS_PCP!G22 -> 0 | J25: =VENDAS_PCP!H22 -> 0 | N25: DUI16 | O25: ALUFORCE CB DUPLEX 16mm² NEUTRO ISOLADO | P25: PT/AZ
A26: P. BRUTO | D26: P.LIQUIDO | F26: LOTE | H26: =H25 -> 0 | N26: DUI25 | O26: ALUFORCE CB DUPLEX 25mm² NEUTRO ISOLADO | P26: PT/AZ
N27: DUI35 | O27: ALUFORCE CB DUPLEX 35mm² NEUTRO ISOLADO | P27: PT/AZ
A28: 6 | B28: =VENDAS_PCP!B23 -> 0 | C28: =IFERROR(VLOOKUP(B13:B56,N19:O175,2,0),"") | F28: =IFERROR(VLOOKUP(B28,N18:P186,3,0),"") | H28: =VENDAS_PCP!F23 -> 0 | I28: =VENDAS_PCP!G23 -> 0 | J28: =VENDAS_PCP!H23 -> 0 | N28: DUI50 | O28: ALUFORCE CB DUPLEX 50mm² NEUTRO ISOLADO | P28: PT/AZ
A29: P. BRUTO | D29: P.LIQUIDO | F29: LOTE | H29: =H28 -> 0 | N29: TRN10 | O29: ALUFORCE CB TRIPLEX 10mm² NEUTRO NÚ | P29: PT/CZ/NU
N30: TRN16 | O30: ALUFORCE CB TRIPLEX 16mm² NEUTRO NÚ | P30: PT/CZ/NU
A31: 7 | B31: =VENDAS_PCP!B24 -> 0 | C31: =IFERROR(VLOOKUP(B13:B56,N19:O180,2,0),"") | F31: =IFERROR(VLOOKUP(B31,N18:P192,3,0),"") | H31: =VENDAS_PCP!F24 -> 0 | I31: =VENDAS_PCP!G24 -> 0 | J31: =VENDAS_PCP!H24 -> 0 | N31: TRN25 | O31: ALUFORCE CB TRIPLEX 25mm² NEUTRO NÚ | P31: PT/CZ/NU
A32: P. BRUTO | D32: P.LIQUIDO | F32: LOTE | H32: =H31 -> 0 | N32: TRN35 | O32: ALUFORCE CB TRIPLEX 35mm² NEUTRO NÚ | P32: PT/CZ/NU
N33: TRN50 | O33: ALUFORCE CB TRIPLEX 50mm² NEUTRO NÚ | P33: PT/CZ/NU
A34: 8 | B34: =VENDAS_PCP!B25 -> 0 | C34: =IFERROR(VLOOKUP(B13:B56,N19:O181,2,0),"") | F34: =IFERROR(VLOOKUP(B34,N18:P192,3,0),"") | H34: =VENDAS_PCP!F25 -> 0 | I34: =VENDAS_PCP!G25 -> 0 | J34: =VENDAS_PCP!H25 -> 0 | N34: TRN50/35 | O34: ALUFORCE CB TRIPLEX 50mm² + 35mm² NEUTRO NÚ | P34: PT/CZ/NU
A35: P. BRUTO | D35: P.LIQUIDO | F35: LOTE | H35: =H34 -> 0 | N35: TRN70 | O35: ALUFORCE CB TRIPLEX 70mm² NEUTRO NÚ | P35: PT/CZ/NU
N36: TRN95/70 | O36: ALUFORCE CB TRIPLEX 95mm² + 70mm² NEUTRO NÚ | P36: PT/CZ/NU
A37: 9 | B37: =VENDAS_PCP!B26 -> 0 | C37: =IFERROR(VLOOKUP(B13:B56,N19:O182,2,0),"") | F37: =IFERROR(VLOOKUP(B37,N18:P188,3,0),"") | H37: =VENDAS_PCP!F26 -> 0 | I37: =VENDAS_PCP!G26 -> 0 | J37: =VENDAS_PCP!H26 -> 0 | N37: TRN95 | O37: ALUFORCE CB TRIPLEX 95mm² NEUTRO NÚ | P37: PT/CZ/NU
A38: P. BRUTO | D38: P.LIQUIDO | F38: LOTE | H38: =H37 -> 0 | N38: TRN120/70 | O38: ALUFORCE CB TRIPLEX 120mm² + 70mm² NEUTRO NÚ | P38: PT/CZ/NU
N39: TRN120/95 | O39: ALUFORCE CB TRIPLEX 120mm² + 95mm² NEUTRO NÚ | P39: PT/CZ/NU
A40: 10 | B40: =VENDAS_PCP!B27 -> 0 | C40: =IFERROR(VLOOKUP(B13:B56,N18:O183,2,0),"") | F40: =IFERROR(VLOOKUP(B40,N18:P196,3,0),"") | H40: =VENDAS_PCP!F27 -> 0 | I40: =VENDAS_PCP!G27 -> 0 | J40: =VENDAS_PCP!H27 -> 0 | N40: TRN120 | O40: ALUFORCE CB TRIPLEX 120mm² NEUTRO NÚ | P40: PT/CZ/NU
A41: P. BRUTO | D41: P.LIQUIDO | F41: LOTE | H41: =H40 -> 0 | N41: TRN150/95 | O41: ALUFORCE CB TRIPLEX 150mm² + 95mm² NEUTRO NÚ | P41: PT/CZ/NU
N42: TRN150/120 | O42: ALUFORCE CB TRIPLEX 150mm² + 120mm² NEUTRO NÚ | P42: PT/CZ/NU
A43: 11 | B43: =VENDAS_PCP!B28 -> 0 | C43: =IFERROR(VLOOKUP(B13:B56,N18:O184,2,0),"") | F43: =IFERROR(VLOOKUP(B43,N18:P193,3,0),"") | H43: =VENDAS_PCP!F28 -> 0 | I43: =VENDAS_PCP!G28 -> 0 | J43: =VENDAS_PCP!H28 -> 0 | N43: TRN150 | O43: ALUFORCE CB TRIPLEX 150mm² NEUTRO NÚ | P43: PT/CZ/NU
A44: P. BRUTO | D44: P.LIQUIDO | F44: LOTE | H44: =H43 -> 0 | N44: TRN185/120 | O44: ALUFORCE CB TRIPLEX 185mm² + 120mm² NEUTRO NÚ | P44: PT/CZ/NU
N45: TRN185/150 | O45: ALUFORCE CB TRIPLEX 185mm² + 150mm² NEUTRO NÚ | P45: PT/CZ/NU
A46: 12 | B46: =VENDAS_PCP!B29 -> 0 | C46: =IFERROR(VLOOKUP(B13:B56,N19:O185,2,0),"") | F46: =IFERROR(VLOOKUP(B46,N18:P197,3,0),"") | H46: =VENDAS_PCP!F29 -> 0 | I46: =VENDAS_PCP!G29 -> 0 | J46: =VENDAS_PCP!H29 -> 0 | N46: TRN185 | O46: ALUFORCE CB TRIPLEX 185mm² NEUTRO NÚ | P46: PT/CZ/NU
A47: P. BRUTO | D47: P.LIQUIDO | F47: LOTE | H47: =H46 -> 0 | N47: TRI10 | O47: ALUFORCE CB TRIPLEX 10mm² NEUTRO ISOLADO | P47: PT/CZ/AZ
N48: TRI16 | O48: ALUFORCE CB TRIPLEX 16mm² NEUTRO ISOLADO | P48: PT/CZ/AZ
A49: 13 | B49: =VENDAS_PCP!B30 -> 0 | C49: =IFERROR(VLOOKUP(B49:B56,N18:O186,2,0),"") | F49: =IFERROR(VLOOKUP(B49,N18:P189,3,0),"") | H49: =VENDAS_PCP!F30 -> 0 | I49: =VENDAS_PCP!G30 -> 0 | J49: =VENDAS_PCP!H30 -> 0 | N49: TRI25 | O49: ALUFORCE CB TRIPLEX 25mm² NEUTRO ISOLADO | P49: PT/CZ/AZ
A50: P. BRUTO | D50: P.LIQUIDO | F50: LOTE | H50: =H49 -> 0 | N50: TRI50/35 | O50: ALUFORCE CB TRIPLEX 50mm² NEUTRO ISOLADO | P50: PT/CZ/AZ
N51: TRI35 | O51: ALUFORCE CB TRIPLEX 35mm² NEUTRO ISOLADO | P51: PT/CZ/AZ
A52: 14 | B52: =VENDAS_PCP!B31 -> 0 | C52: =IFERROR(VLOOKUP(B12:B56,N18:O187,2,0),"") | F52: =IFERROR(VLOOKUP(B52,N18:P190,3,0),"") | H52: =VENDAS_PCP!F31 -> 0 | I52: =VENDAS_PCP!G31 -> 0 | J52: =VENDAS_PCP!H31 -> 0 | N52: TRI50 | O52: ALUFORCE CB TRIPLEX 50mm² NEUTRO ISOLADO | P52: PT/CZ/AZ
A53: P. BRUTO | D53: P.LIQUIDO | F53: LOTE | H53: =H52 -> 0 | N53: TRI70 | O53: ALUFORCE CB TRIPLEX 70mm² NEUTRO ISOLADO | P53: PT/CZ/AZ
N54: TRI95/70 | O54: ALUFORCE CB TRIPLEX 95mm² + 70mm² NEUTRO ISOLADO | P54: PT/CZ/AZ
A55: 15 | B55: =VENDAS_PCP!B32 -> 0 | C55: =IFERROR(VLOOKUP(B13:B56,N19:O188,2,0),"") | F55: =IFERROR(VLOOKUP(B55,N18:P196,3,0),"") | H55: =VENDAS_PCP!F32 -> 0 | I55: =VENDAS_PCP!G32 -> 0 | J55: =VENDAS_PCP!H32 -> 0 | N55: TRI95 | O55: ALUFORCE CB TRIPLEX 95mm² NEUTRO ISOLADO | P55: PT/CZ/AZ
A56: P. BRUTO | D56: P.LIQUIDO | F56: LOTE | H56: =H55 -> 0 | N56: TRI120/70 | O56: ALUFORCE CB TRIPLEX 120mm² + 70mm² NEUTRO ISOLADO | P56: PT/CZ/AZ
N57: TRI120/95 | O57: ALUFORCE CB TRIPLEX 120mm² + 95mm² NEUTRO ISOLADO | P57: PT/CZ/AZ
A58: QTD - VOLUME: | D58: __________________________ | F58: EMBALAGEM: | H58: ___________________________ | N58: TRI120 | O58: ALUFORCE CB TRIPLEX 120mm² NEUTRO ISOLADO | P58: PT/CZ/AZ
A59: P. BRUTO | N59: TRI150/95 | O59: ALUFORCE CB TRIPLEX 150mm² + 95mm² NEUTRO ISOLADO | P59: PT/CZ/AZ
A60: P. LIQUIDO | E60: OBSERVAÇÕES: | N60: TRI150/120 | O60: ALUFORCE CB TRIPLEX 150mm² + 120mm² NEUTRO ISOLADO | P60: PT/CZ/AZ
E61: =VENDAS_PCP!E51 -> 0 | N61: TRI150 | O61: ALUFORCE CB TRIPLEX 150mm² NEUTRO ISOLADO | P61: PT/CZ/AZ
C62: COMPLETO | N62: TRI185/120 | O62: ALUFORCE CB TRIPLEX 185mm² + 120mm² NEUTRO ISOLADO | P62: PT/CZ/AZ
N63: TRI185/150 | O63: ALUFORCE CB TRIPLEX 185mm² + 150mm² NEUTRO ISOLADO | P63: PT/CZ/AZ
C64: PARCIAL | N64: TRI185 | O64: ALUFORCR CB TRIPLEX 185mm² NEUTRO ISOLADO | P64: PT/CZ/AZ
N65: QDN10 | O65: ALUFORCE CB QUAD 10mm² NEUTRO NÚ | P65: PT/CZ/VM/NU
N66: QDN16 | O66: ALUFORCE CB QUAD 16mm² NEUTRO NÚ | P66: PT/CZ/VM/NU
N67: QDN25 | O67: ALUFORCE CB QUAD 25mm² NEUTRO NÚ | P67: PT/CZ/VM/NU
N68: QDN35 | O68: ALUFORCE CB QUAD 35mm² NEUTRO NÚ | P68: PT/CZ/VM/NU
N69: QDN35/70 | O69: ALUFORCE CB QUAD 35mm² + 70 mm² NEUTRO NÚ | P69: PT/CZ/VM/NU
N70: QDN50/35 | O70: ALUFORCE CB QUAD 50mm² + 35 mm² NEUTRO NÚ | P70: PT/CZ/VM/NU
N71: QDN50 | O71: ALUFORCE CB QUAD 50mm² NEUTRO NÚ | P71: PT/CZ/VM/NU
N72: QDN50/70 | O72: ALUFORCE CB QUAD 50mm² + 70 mm² NEUTRO NÚ | P72: PT/CZ/VM/NU
N73: CLIP3,0 | O73: CLIP NASAL MOD.F1 PL/AL 3,0MM | P73: BRANCO
N74: QDN70/35 | O74: ALUFORCE CB QUAD 70mm² + 35 mm² NEUTRO NÚ | P74: PT/CZ/VM/NU
N75: QDN70/50 | O75: ALUFORCE CB QUAD 70mm² + 50 mm² NEUTRO NÚ | P75: PT/CZ/VM/NU
N76: QDN70 | O76: ALUFORCE CB QUAD 70mm² NEUTRO NÚ | P76: PT/CZ/VM/NU
... N146: CET4.60 | O146: ALUFORCE CB DE POTÊNCIA 4x6,0mm² 0,6/1KV NBR 7286 AL/HEPR | P146: AM/VD/VM/PT
N147: CET5.15 | O147: ALUFORCE CB DE POTÊNCIA 5x1,5mm² 0,6/1KV NBR 7286 AL/HEPR
N148: CET5.25 | O148: ALUFORCE CB DE POTÊNCIA 5x2,5mm² 0,6/1KV NBR 7286 AL/HEPR
N149: CET5.40 | O149: ALUFORCE CB DE POTÊNCIA 5x4,0mm² 0,6/1KV NBR 7286 AL/HEPR
N150: CET5.60 | O150: ALUFORCE CB DE POTÊNCIA 5x6,0mm² 0,6/1KV NBR 7286 AL/HEPR
N151: CET7.15 | O151: ALUFORCE CB DE POTÊNCIA 7x1,5mm² 0,6/1KV NBR 7286 AL/HEPR | P151: AM/VD/VM/AZ/PT/BC/MR
N152: CET8.15 | O152: ALUFORCE CB DE POTÊNCIA 8x1,5mm² 0,6/1KV NBR 7286 AL/HEPR | P152: AM/VD/VM/AZ/PT/BC/LR/MR
N153: POT10 | O153: ALUFORCE CB DE POTÊNCIA 10 mm² 0,6/1KV NBR 7287 AL/XLPE/PVC | P153: PT
N154: POT16 | O154: ALUFORCE CB DE POTÊNCIA 16 mm² 0,6/1KV NBR 7287 AL/XLPE/PVC | P154: PT
N155: POT25 | O155: ALUFORCE CB DE POTÊNCIA 25 mm² 0,6/1KV NBR 7287 AL/XLPE/PVC | P155: PT
N156: POT35 | O156: ALUFORCE CB DE POTÊNCIA 35 mm² 0,6/1KV NBR 7287 AL/XLPE/PVC | P156: PT
N157: POT50 | O157: ALUFORCE CB DE POTÊNCIA 50 mm² 0,6/1KV NBR 7287 AL/XLPE/PVC | P157: PT
N158: POT70 | O158: ALUFORCE CB DE POTÊNCIA 70 mm² 0,6/1KV NBR 7287 AL/XLPE/PVC | P158: PT
N159: POT95 | O159: ALUFORCE CB DE POTÊNCIA 95 mm² 0,6/1KV NBR 7287 AL/XLPE/PVC | P159: PT
N160: POT120 | O160: ALUFORCE CB DE POTÊNCIA 120 mm² 0,6/1KV NBR 7287 AL/XLPE/PVC | P160: PT
N161: POT150 | O161: ALUFORCE CB DE POTÊNCIA 150 mm² 0,6/1KV NBR 7287 AL/XLPE/PVC | P161: PT
N162: POT185 | O162: ALUFORCE CB DE POTÊNCIA 185 mm² 0,6/1KV NBR 7287 AL/XLPE/PVC | P162: PT
N163: POT240 | O163: ALUFORCE CB DE POTÊNCIA 240 mm² 0,6/1KV NBR 7287 AL/XLPE/PVC | P163: PT
N164: PEAC | O164: ALUFORCE CB CA PEACHBELL
N165: ROSE | O165: ALUFORCE CB CA ROSE
N166: IRIS | O166: ALUFORCE CB CA IRIS
N167: PANS | O167: ALUFORCE CB CA PANSY
N168: POPP | O168: ALUFORCE CB CA POPPY
N169: ASTE | O169: ALUFORCE CB CA ASTER
N170: PHLO | O170: ALUFORCE CB CA PHLOX
N171: OXLI | O171: ALUFORCE CB CA OXLIP
N172: SNEE | O172: ALUFORCE CB CA SNEEZEWORT
...
